sphinx_py3doc_enhanced_theme/__init__.py
sphinx_py3doc_enhanced_theme/themes/sphinx_py3doc_enhanced_theme/globaltoc.html
sphinx_py3doc_enhanced_theme/themes/sphinx_py3doc_enhanced_theme/layout.html
sphinx_py3doc_enhanced_theme/themes/sphinx_py3doc_enhanced_theme/theme.conf
sphinx_py3doc_enhanced_theme/themes/sphinx_py3doc_enhanced_theme/static/copybutton.js
sphinx_py3doc_enhanced_theme/themes/sphinx_py3doc_enhanced_theme/static/favicon.png
sphinx_py3doc_enhanced_theme/themes/sphinx_py3doc_enhanced_theme/static/pydoctheme.css_t
sphinx_py3doc_enhanced_theme/themes/sphinx_py3doc_enhanced_theme/static/right-red@2x.png
sphinx_py3doc_enhanced_theme/themes/sphinx_py3doc_enhanced_theme/static/sidebar.js
sphinx_py3doc_enhanced_theme-2.4.0.dist-info/DESCRIPTION.rst
sphinx_py3doc_enhanced_theme-2.4.0.dist-info/METADATA
sphinx_py3doc_enhanced_theme-2.4.0.dist-info/RECORD
sphinx_py3doc_enhanced_theme-2.4.0.dist-info/WHEEL
sphinx_py3doc_enhanced_theme-2.4.0.dist-info/entry_points.txt
sphinx_py3doc_enhanced_theme-2.4.0.dist-info/metadata.json
sphinx_py3doc_enhanced_theme-2.4.0.dist-info/top_level.txt
